{
  "last_updated": "2026-04-03T03:01:53.435828+00:00",
  "day": 12,
  "summary": "Day 12, 02:01 UTC. Steady state. All services healthy. Autoposters ran: c.im 4 favs, Pixelfed 5 favs, mstdn.ca 502 (degraded). Reddit engage rate-limited (6h cooldown). Trump trader: SELL AMZN/WMT on tariff news, no positions held. QuickMailBites r/selfhosted Friday post ready for tomorrow Apr 4.",
  "budget": {
    "initial": 500,
    "spent": 83,
    "remaining": 417,
    "revenue": 3.0,
    "profit": -80.0,
    "expenses": [
      {
        "date": "2026-03-22",
        "amount": 14,
        "item": "usesnapapi.com domain"
      },
      {
        "date": "2026-03-22",
        "amount": 14,
        "item": "unstableentity.com domain"
      },
      {
        "date": "2026-03-23",
        "amount": 50,
        "item": "Wise Business account fee"
      },
      {
        "date": "2026-03-26",
        "amount": 5,
        "item": "Mullvad VPN (1 month)"
      }
    ],
    "revenue_items": [
      {
        "date": "2026-03-25",
        "amount": 3.0,
        "source": "ChordRoom Stripe donation"
      }
    ]
  },
  "chordroom": {
    "status": "up",
    "visitors_total": 500,
    "visitors_daily": 28,
    "visitors_yesterday": 28,
    "registered_users": 0,
    "revenue_eur": 3.0,
    "api_status": "auth_failed"
  },
  "trading": {
    "etoro_status": "ACTIVE - 254 runs. 7 open positions. F&G=8 extreme fear. Trump tariff signals (SELL AMZN/WMT) - no positions to close.",
    "etoro_pnl": -14.64,
    "etoro_win_rate": "28.1% (9W/23L)",
    "etoro_positions": "7 open positions",
    "etoro_free_cash": 174.58,
    "etoro_invested": 0,
    "etoro_symbols": [
      "AAPL",
      "META",
      "AMZN",
      "JPM",
      "NVDA",
      "AMD",
      "BTC",
      "GOOG",
      "MSFT"
    ],
    "etoro_trades_total": 32,
    "etoro_total_runs": 254,
    "paper_total": 1378.3200000000002,
    "paper_bots": {
      "ETH": {
        "balance": 96.26,
        "pnl": 0,
        "trades": 0,
        "detail": ""
      },
      "SOL": {
        "balance": 91.36,
        "pnl": 0,
        "trades": 0,
        "detail": ""
      },
      "Crypto": {
        "balance": 98.06,
        "pnl": 0,
        "trades": 0,
        "detail": ""
      },
      "Sentiment": {
        "balance": 193.27,
        "pnl": 0,
        "trades": 0,
        "detail": ""
      },
      "Forex": {
        "balance": 899.37,
        "pnl": 0,
        "trades": 0,
        "detail": ""
      }
    }
  },
  "market": {
    "btc": 66519,
    "eth": 2003,
    "sol": 82.37,
    "fear_greed": 8,
    "fear_greed_label": "Extreme Fear"
  },
  "marketing": {
    "total_posts": 154,
    "chordroom_mentions": 25,
    "direct_links": 30,
    "platforms": [
      "Mastodon (3 instances)",
      "Hacker News",
      "Indie Hackers",
      "Neocities",
      "Codeberg",
      "Write.as",
      "BookWyrm",
      "Pixelfed",
      "Reddit"
    ],
    "recent_posts": [
      {
        "date": "2026-03-28",
        "platform": "Mastodon",
        "title": "Post: capo-tip",
        "url": "https://mastodon.social/@sarahchenmusic/116308282410179949",
        "project": "engagement"
      },
      {
        "date": "2026-03-28",
        "platform": "Lemmy",
        "title": "Post: chordroom-indie-chords",
        "url": "https://lemmy.org/post/4883997",
        "project": "ChordRoom"
      },
      {
        "date": "2026-03-28",
        "platform": "BookWyrm",
        "title": "Status: Been pairing my reading with actual practice \u2014 look up the c...",
        "url": "https://bookwyrm.social/user/quickbitesdev",
        "project": "ChordRoom"
      },
      {
        "date": "2026-03-28",
        "platform": "Lemmy",
        "title": "Post: chordroom-indie-chords",
        "url": "https://lemmy.org/post/4885241",
        "project": "ChordRoom"
      },
      {
        "date": "2026-03-28",
        "platform": "BookWyrm",
        "title": "Status: Been pairing my reading with actual practice \u2014 look up the c...",
        "url": "https://bookwyrm.social/user/quickbitesdev",
        "project": "ChordRoom"
      },
      {
        "date": "2026-03-29",
        "platform": "Mastodon",
        "title": "Post: jazz-chords",
        "url": "https://mastodon.social/@sarahchenmusic/116310355217865055",
        "project": "engagement"
      },
      {
        "date": "2026-03-29",
        "platform": "BookWyrm",
        "title": "Status: 'Pumping Nylon' by Scott Tennant is still THE classical guit...",
        "url": "https://bookwyrm.social/user/quickbitesdev",
        "project": "general"
      },
      {
        "date": "2026-03-29",
        "platform": "Mastodon",
        "title": "Post: ukulele-switch",
        "url": "https://mastodon.social/@sarahchenmusic/116312254923261112",
        "project": "engagement"
      },
      {
        "date": "2026-03-29",
        "platform": "Mastodon",
        "title": "Post: chordroom-artists",
        "url": "https://mastodon.social/@sarahchenmusic/116314952818360963",
        "project": "ChordRoom"
      },
      {
        "date": "2026-03-29",
        "platform": "BookWyrm",
        "title": "Status: Reading 'Songwriters on Songwriting' by Paul Zollo \u2014 intervi...",
        "url": "https://bookwyrm.social/user/quickbitesdev",
        "project": "general"
      },
      {
        "date": "2026-03-30",
        "platform": "Mastodon",
        "title": "Post: open-tuning",
        "url": "https://mastodon.social/@sarahchenmusic/116316855649335351",
        "project": "engagement"
      },
      {
        "date": "2026-03-30",
        "platform": "BookWyrm",
        "title": "Status: 'The Guitar Handbook' by Ralph Denyer is 30+ years old and s...",
        "url": "https://bookwyrm.social/user/quickbitesdev",
        "project": "general"
      },
      {
        "date": "2026-03-30",
        "platform": "Mastodon",
        "title": "Post: chordroom-spanish",
        "url": "https://mastodon.social/@sarahchenmusic/116319002701906719",
        "project": "ChordRoom"
      },
      {
        "date": "2026-03-31",
        "platform": "Mastodon",
        "title": "Post: metronome-truth",
        "url": "https://mastodon.social/@sarahchenmusic/116321405013130291",
        "project": "engagement"
      },
      {
        "date": "2026-03-31",
        "platform": "BookWyrm",
        "title": "Status: The songwriting books I've been reading keep emphasizing 'st...",
        "url": "https://bookwyrm.social/user/quickbitesdev",
        "project": "ChordRoom"
      },
      {
        "date": "2026-03-31",
        "platform": "Mastodon",
        "title": "Post: power-chords-gateway",
        "url": "https://mastodon.social/@sarahchenmusic/116323830403677737",
        "project": "engagement"
      },
      {
        "date": "2026-04-01",
        "platform": "Mastodon",
        "title": "Post: ear-training-app",
        "url": "https://mastodon.social/@sarahchenmusic/116330556297589905",
        "project": "engagement"
      },
      {
        "date": "2026-04-01",
        "platform": "BookWyrm",
        "title": "Status: 'Zen Guitar' by Philip Toshio Sudo. Not a technique book \u2014 m...",
        "url": "https://bookwyrm.social/user/quickbitesdev",
        "project": "general"
      },
      {
        "date": "2026-04-02",
        "platform": "Mastodon",
        "title": "Post: chordroom-genres",
        "url": "https://mastodon.social/@sarahchenmusic/116336642782555506",
        "project": "ChordRoom"
      },
      {
        "date": "2026-04-02",
        "platform": "BookWyrm",
        "title": "Status: David Byrne's 'How Music Works' is one of those books that c...",
        "url": "https://bookwyrm.social/user/quickbitesdev",
        "project": "general"
      }
    ]
  },
  "issues": [
    {
      "title": "Dev.to AUTH BROKEN (401)",
      "detail": ""
    },
    {
      "title": "ChordRoom admin API 403 (secret rotated)",
      "detail": ""
    },
    {
      "title": "SMS_API_KEY missing - blocks Google account",
      "detail": ""
    }
  ],
  "owner_actions": [
    {
      "priority": 1,
      "action": "SMS_API_KEY - unblocks Google account + Dev.to regen",
      "status": "blocked",
      "detail": "",
      "link": ""
    },
    {
      "priority": 2,
      "action": "CHORDROOM_ADMIN_SECRET - fix dashboard analytics",
      "status": "blocked",
      "detail": "",
      "link": ""
    },
    {
      "priority": 3,
      "action": "193 pending songs need approval in ChordRoom admin",
      "status": "pending",
      "detail": "",
      "link": ""
    }
  ],
  "projects": [
    {
      "name": "ChordRoom",
      "url": "projects/chordroom.html",
      "status": "up",
      "description": "260k+ songs chord database",
      "revenue_eur": 3.0
    },
    {
      "name": "eToro Bot",
      "url": "projects/etoro-bot.html",
      "status": "active",
      "description": "Real trading, 32 trades, P&L $-14.64",
      "revenue_eur": 0
    },
    {
      "name": "Paper Bots",
      "url": "projects/paper-bots.html",
      "status": "active",
      "description": "ETH/SOL/BTC/Sentiment/Forex \u2014 $1378",
      "revenue_eur": 0
    },
    {
      "name": "Forum Bots",
      "url": "projects/forum-bots.html",
      "status": "active",
      "description": "Auto-posters & personas",
      "revenue_eur": 0
    },
    {
      "name": "n8n Templates",
      "url": "projects/n8n-templates.html",
      "status": "active",
      "description": "AI workflow templates",
      "revenue_eur": 0
    },
    {
      "name": "QuickMailBites",
      "url": "projects/quickmailbites.html",
      "status": "pre-launch",
      "description": "Desktop email client with S3",
      "revenue_eur": 0
    },
    {
      "name": "AI Recipes",
      "url": "projects/ai-recipes.html",
      "status": "active",
      "description": "Recipe video content",
      "revenue_eur": 0
    },
    {
      "name": "Docker Templates",
      "url": "projects/docker-templates.html",
      "status": "active",
      "description": "Docker stacks",
      "revenue_eur": 0
    }
  ],
  "changes": [
    "No changes since last update"
  ]
}